mridc/__init__.py
mridc/constants.py
mridc/launch.py
mridc/package_info.py
mridc/collections/__init__.py
mridc/collections/common/__init__.py
mridc/collections/common/callbacks/__init__.py
mridc/collections/common/callbacks/callbacks.py
mridc/collections/common/data/__init__.py
mridc/collections/common/data/dataset.py
mridc/collections/common/losses/__init__.py
mridc/collections/common/losses/aggregator.py
mridc/collections/common/losses/ssim.py
mridc/collections/common/metrics/__init__.py
mridc/collections/common/metrics/global_average_loss_metric.py
mridc/collections/common/parts/__init__.py
mridc/collections/common/parts/fft.py
mridc/collections/common/parts/patch_utils.py
mridc/collections/common/parts/ptl_overrides.py
mridc/collections/common/parts/rnn_utils.py
mridc/collections/common/parts/training_utils.py
mridc/collections/common/parts/utils.py
mridc/collections/quantitative/__init__.py
mridc/collections/quantitative/data/__init__.py
mridc/collections/quantitative/data/qmri_data.py
mridc/collections/quantitative/models/__init__.py
mridc/collections/quantitative/models/base.py
mridc/collections/quantitative/models/qcirim.py
mridc/collections/quantitative/models/qvn.py
mridc/collections/quantitative/models/qrim/__init__.py
mridc/collections/quantitative/models/qrim/qrim_block.py
mridc/collections/quantitative/models/qrim/utils.py
mridc/collections/quantitative/models/qvarnet/__init__.py
mridc/collections/quantitative/models/qvarnet/qvn_block.py
mridc/collections/quantitative/parts/__init__.py
mridc/collections/quantitative/parts/transforms.py
mridc/collections/reconstruction/__init__.py
mridc/collections/reconstruction/data/__init__.py
mridc/collections/reconstruction/data/mri_data.py
mridc/collections/reconstruction/data/subsample.py
mridc/collections/reconstruction/metrics/__init__.py
mridc/collections/reconstruction/metrics/evaluate.py
mridc/collections/reconstruction/models/__init__.py
mridc/collections/reconstruction/models/base.py
mridc-0.2.0.dist-info/LICENSE
mridc-0.2.0.dist-info/METADATA
mridc-0.2.0.dist-info/WHEEL
mridc-0.2.0.dist-info/top_level.txt
mridc-0.2.0.dist-info/RECORD
