Metadata-Version: 2.1
Name: mridc
Version: 0.2.0
Summary: Data Consistency for Magnetic Resonance Imaging
Home-page: https://github.com/wdika/mridc
Download-URL: https://github.com/wdika/mridc/releases
Author: Dimitrios Karkalousos
Author-email: d.karkalousos@amsterdamumc.nl
Maintainer: Dimitrios Karkalousos
Maintainer-email: d.karkalousos@amsterdamumc.nl
License: Apache-2.0 License
Keywords: machine-learning,deep-learning,compressed-sensing,pytorch,mri,medical-imaging,convolutional-neural-networks,unet,medical-image-processing,medical-image-analysis,data-consistency,mri-reconstruction,fastmri,recurrent-inference-machines,variational-network,cirim
Classifier: Development Status :: 5 - Production/Stable
Classifier: Intended Audience :: Developers
Classifier: Intended Audience :: Science/Research
Classifier: Intended Audience :: Information Technology
Classifier: Topic :: Scientific/Engineering
Classifier: Topic :: Scientific/Engineering :: Mathematics
Classifier: Topic :: Scientific/Engineering :: Physics
Classifier: Topic :: Scientific/Engineering :: Artificial Intelligence
Classifier: Topic :: Software Development :: Libraries
Classifier: Topic :: Software Development :: Libraries :: Python Modules
Classifier: Topic :: Utilities
Classifier: License :: OSI Approved :: Apache Software License
Classifier: Programming Language :: Python :: 3
Classifier: Programming Language :: Python :: 3.8
Classifier: Programming Language :: Python :: 3.9
Classifier: Environment :: Console
Classifier: Natural Language :: English
Classifier: Operating System :: OS Independent
License-File: LICENSE
Requires-Dist: defusedxml (>=0.7.1)
Requires-Dist: h5py (>=3.6.0)
Requires-Dist: hydra-core (==1.1.0)
Requires-Dist: myst-parser (>=0.17.2)
Requires-Dist: numba (>=0.54.1)
Requires-Dist: numpy (>=1.20.3)
Requires-Dist: omegaconf (==2.1.2)
Requires-Dist: onnx (>=1.11.0)
Requires-Dist: onnxruntime (>=1.11.1)
Requires-Dist: packaging (>=21.3)
Requires-Dist: pandas (>=1.3.4)
Requires-Dist: ptwt (>=0.1.2)
Requires-Dist: pytest (>=7.1.2)
Requires-Dist: python-dateutil (>=2.8.2)
Requires-Dist: pytorch-lightning (>=1.6.0)
Requires-Dist: PyYAML (>=5.3.1)
Requires-Dist: runstats (>=2.0.0)
Requires-Dist: scikit-image (>=0.18.3)
Requires-Dist: setuptools (>=62.3.2)
Requires-Dist: sphinx (>=4.5.0)
Requires-Dist: sphinx-rtd-theme (>=1.0.0)
Requires-Dist: sphinxcontrib-apidoc (>=0.3.0)
Requires-Dist: torch (>=1.8.0)
Requires-Dist: torchmetrics (>=0.6.1)
Requires-Dist: tqdm (>=4.62.3)
Requires-Dist: wandb (>=0.12.17)
Requires-Dist: wget (>=3.2)
Requires-Dist: wrapt (>=1.13.3)
